YijianWakuangGainianZongjie20211019Fix1/README.md
YijianWakuangGainianZongjie20211019Fix1/__init__.py
YijianWakuangGainianZongjie20211019Fix1/__main__.py
YijianWakuangGainianZongjie20211019Fix1/file.epub
YijianWakuangGainianZongjie20211019Fix1/index.html
YijianWakuangGainianZongjie20211019Fix1/css/__init__.py
YijianWakuangGainianZongjie20211019Fix1/css/annotations.css
YijianWakuangGainianZongjie20211019Fix1/css/main.css
YijianWakuangGainianZongjie20211019Fix1/css/normalize.css
YijianWakuangGainianZongjie20211019Fix1/css/popup.css
YijianWakuangGainianZongjie20211019Fix1/font/__init__.py
YijianWakuangGainianZongjie20211019Fix1/font/fontello.eot
YijianWakuangGainianZongjie20211019Fix1/font/fontello.svg
YijianWakuangGainianZongjie20211019Fix1/font/fontello.ttf
YijianWakuangGainianZongjie20211019Fix1/font/fontello.woff
YijianWakuangGainianZongjie20211019Fix1/img/__init__.py
YijianWakuangGainianZongjie20211019Fix1/img/annotator-glyph-sprite.png
YijianWakuangGainianZongjie20211019Fix1/img/annotator-icon-sprite.png
YijianWakuangGainianZongjie20211019Fix1/img/apple-touch-icon.png
YijianWakuangGainianZongjie20211019Fix1/img/cancelfullscreen.png
YijianWakuangGainianZongjie20211019Fix1/img/close.png
YijianWakuangGainianZongjie20211019Fix1/img/fullscreen.png
YijianWakuangGainianZongjie20211019Fix1/img/loader.gif
YijianWakuangGainianZongjie20211019Fix1/img/menu-icon.png
YijianWakuangGainianZongjie20211019Fix1/img/save.png
YijianWakuangGainianZongjie20211019Fix1/img/saved.png
YijianWakuangGainianZongjie20211019Fix1/img/settings-s.png
YijianWakuangGainianZongjie20211019Fix1/img/settings.png
YijianWakuangGainianZongjie20211019Fix1/img/star.png
YijianWakuangGainianZongjie20211019Fix1/js/__init__.py
YijianWakuangGainianZongjie20211019Fix1/js/epub.js
YijianWakuangGainianZongjie20211019Fix1/js/epub.min.js
YijianWakuangGainianZongjie20211019Fix1/js/epub.min.map
YijianWakuangGainianZongjie20211019Fix1/js/hooks.min.js
YijianWakuangGainianZongjie20211019Fix1/js/hooks.min.map
yijian_wakuang_gainian_zongjie_20211019_fix1-2025.3.25.0.dist-info/METADATA
yijian_wakuang_gainian_zongjie_20211019_fix1-2025.3.25.0.dist-info/WHEEL
yijian_wakuang_gainian_zongjie_20211019_fix1-2025.3.25.0.dist-info/entry_points.txt
yijian_wakuang_gainian_zongjie_20211019_fix1-2025.3.25.0.dist-info/top_level.txt
yijian_wakuang_gainian_zongjie_20211019_fix1-2025.3.25.0.dist-info/RECORD
